linflex/__init__.py
linflex/_class_constant.py
linflex/_numerical_tools.py
linflex/_vec2.py
linflex/_vec2i.py
linflex/_vec3.py
linflex/py.typed
linflex/typing.py
linflex-0.3.3.dist-info/WHEEL
linflex-0.3.3.dist-info/METADATA
linflex-0.3.3.dist-info/RECORD
