Metadata-Version: 2.3
Name: linflex
Version: 0.3.3
Summary: A linear algebra package written in Python
Author: Havsalt
Author-email: Havsalt <77575424+Havsalt@users.noreply.github.com>
License: MIT License
Classifier: Development Status :: 4 - Beta
Classifier: Intended Audience :: Developers
Classifier: Natural Language :: English
Classifier: Operating System :: OS Independent
Classifier: Programming Language :: Python :: 3
Classifier: Programming Language :: Python :: 3 :: Only
Classifier: Programming Language :: Python :: 3.10
Classifier: Programming Language :: Python :: 3.11
Classifier: Programming Language :: Python :: 3.12
Classifier: Programming Language :: Python :: 3.13
Classifier: Programming Language :: Python :: Implementation :: CPython
Classifier: Programming Language :: Python :: Implementation :: PyPy
Classifier: Topic :: Software Development
Classifier: Topic :: Utilities
Classifier: Typing :: Typed
Requires-Dist: typing-extensions>=4.4.0 ; python_full_version < '3.11'
Requires-Python: >=3.10
Project-URL: Source, https://github.com/havsalt/linflex.git
